shadows/__init__.py
shadows/_version.py
shadows/anndatashadow.py
shadows/compat.py
shadows/datashadow.py
shadows/elemshadow.py
shadows/mudatashadow.py
shadows-0.1a2.dist-info/METADATA
shadows-0.1a2.dist-info/WHEEL
shadows-0.1a2.dist-info/licenses/LICENSE
shadows-0.1a2.dist-info/RECORD
