Metadata-Version: 2.3
Name: shadows
Version: 0.1a2
Summary: Low-memory data interfaces for scverse
Project-URL: Documentation, https://scverse.github.io/shadows
Project-URL: Source, https://github.com/scverse/shadows
Project-URL: Home-page, https://github.com/scverse/shadows
Author: Danila Bredikhin
Maintainer-email: Danila Bredikhin <danila@stanford.edu>
License: BSD 3-Clause License
Classifier: Development Status :: 3 - Alpha
Classifier: Intended Audience :: Science/Research
Classifier: License :: OSI Approved :: BSD License
Classifier: Operating System :: OS Independent
Classifier: Programming Language :: Python :: 3
Classifier: Topic :: Scientific/Engineering :: Bio-Informatics
Requires-Python: >=3.10
Provides-Extra: all
Requires-Dist: anndata>=0.8; extra == 'all'
Requires-Dist: mudata>=0.2; extra == 'all'
Requires-Dist: scipy; extra == 'all'
Provides-Extra: dev
Requires-Dist: setuptools-scm; extra == 'dev'
Provides-Extra: doc
Requires-Dist: furo; extra == 'doc'
Requires-Dist: ipython; extra == 'doc'
Requires-Dist: myst-parser; extra == 'doc'
Requires-Dist: nbsphinx; extra == 'doc'
Requires-Dist: pygments; extra == 'doc'
Requires-Dist: readthedocs-sphinx-search; extra == 'doc'
Requires-Dist: sphinx; extra == 'doc'
Requires-Dist: sphinx-autodoc-typehints; extra == 'doc'
Requires-Dist: sphinx-automodapi; extra == 'doc'
Requires-Dist: sphinx-book-theme; extra == 'doc'
Requires-Dist: sphinxcontrib-bibtex; extra == 'doc'
Provides-Extra: test
Requires-Dist: anndata; extra == 'test'
Requires-Dist: mudata; extra == 'test'
Requires-Dist: pqdata; extra == 'test'
Requires-Dist: pytest; extra == 'test'
Requires-Dist: pytest-cov; extra == 'test'
Requires-Dist: scipy; extra == 'test'
Requires-Dist: zarr; extra == 'test'
